{
  "tag": "циклы",
  "name": "Циклы в C#",
  "description": "for, while, do-while",
  "totalTasks": 20,
  "difficultyLevels": [
    {
      "level": 1,
      "tasks": [
        {
          "id": 701,
          "title": "Счет от 1 до 10",
          "description": "Выведите числа от 1 до 10.",
          "requirements": [
            "Использовать цикл for"
          ],
          "hint": "for (int i = 1; i <= 10; i++)",
          "exampleConsoleOutput": "1 2 3 4 5 6 7 8 9 10"
        },
        {
          "id": 702,
          "title": "Сумма чисел",
          "description": "Найдите сумму чисел от 1 до N.",
          "requirements": [
            "N вводит пользователь"
          ],
          "hint": "Сумма = N * (N + 1) / 2",
          "exampleConsoleOutput": "Введите N: 100\nСумма: 5050"
        }
      ]
    },
    {
      "level": 2,
      "tasks": [
        {
          "id": 801,
          "title": "Таблица умножения",
          "description": "Выведите таблицу умножения для числа N.",
          "requirements": [],
          "hint": "Два вложенных цикла",
          "exampleConsoleOutput": "5 x 1 = 5\n5 x 2 = 10\n..."
        }
      ]
    },
    {
      "level": 3,
      "tasks": [
        {
          "id": 901,
          "title": "Простые числа",
          "description": "Найдите все простые числа до N.",
          "requirements": [
            "Использовать вложенные циклы"
          ],
          "hint": "Решето Эратосфена",
          "exampleConsoleOutput": "Простые числа до 20: 2 3 5 7 11 13 17 19"
        }
      ]
    }
  ]
}